torchwatch/__init__.py
torchwatch-0.0.0.dist-info/DESCRIPTION.rst
torchwatch-0.0.0.dist-info/METADATA
torchwatch-0.0.0.dist-info/RECORD
torchwatch-0.0.0.dist-info/WHEEL
torchwatch-0.0.0.dist-info/metadata.json
torchwatch-0.0.0.dist-info/top_level.txt
